uqef/UQsim.py
uqef/__init__.py
uqef/model/Model.py
uqef/model/TestModel.py
uqef/model/__init__.py
uqef/nodes/Nodes.py
uqef/nodes/__init__.py
uqef/schedule/__init__.py
uqef/schedule/defs.py
uqef/schedule/functions.py
uqef/schedule/heuristics.py
uqef/simulation/EnsembleSimulation.py
uqef/simulation/McSimulation.py
uqef/simulation/SaltelliSimulation.py
uqef/simulation/ScSimulation.py
uqef/simulation/Simulation.py
uqef/simulation/__init__.py
uqef/solver/LinearSolver.py
uqef/solver/MpiPoolSolver.py
uqef/solver/MpiSolver.py
uqef/solver/ParallelSolver.py
uqef/solver/Solver.py
uqef/solver/SolverTimes.py
uqef/solver/__init__.py
uqef/stat/RuntimeStatistics.py
uqef/stat/Statistics.py
uqef/stat/TestModelStatistics.py
uqef/stat/__init__.py
uqef/util/TimeMeasurement.py
uqef/util/__init__.py
uqef-0.4.dist-info/licenses/LICENSE.txt
uqef-0.4.dist-info/METADATA
uqef-0.4.dist-info/WHEEL
uqef-0.4.dist-info/top_level.txt
uqef-0.4.dist-info/RECORD
